hkvfewspy/__init__.py
hkvfewspy/io/__init__.py
hkvfewspy/io/rest_fewspi.py
hkvfewspy/io/soap_fewspi.py
hkvfewspy/schemas/__init__.py
hkvfewspy/schemas/timeseries.py
hkvfewspy/utils/__init__.py
hkvfewspy/utils/pi_helper.py
hkvfewspy/utils/query_helper.py
hkvfewspy/utils/simplenamespace.py
hkvfewspy/utils/untangle.py
hkvfewspy-1.0.2.dist-info/LICENSE
hkvfewspy-1.0.2.dist-info/METADATA
hkvfewspy-1.0.2.dist-info/WHEEL
hkvfewspy-1.0.2.dist-info/dependency_links.txt
hkvfewspy-1.0.2.dist-info/top_level.txt
hkvfewspy-1.0.2.dist-info/RECORD
