Metadata-Version: 2.1
Name: hkvfewspy
Version: 1.0.2
Summary: HKV tools voor operationeel waterbeheer
Author: Mattijn van Hoek
Author-email: mattijn.vanhoek@hkv.nl
License-File: LICENSE
Requires-Dist: zeep (>=3.0.0)
Requires-Dist: pytz
Requires-Dist: numpy
Requires-Dist: pandas
Requires-Dist: fire
Requires-Dist: requests
